[
  {
    "id": 1,
    "name": "Ovos Mexidos Clássicos",
    "category": "Café da Manhã",
    "prepTime": 5,
    "cost": 3.50,
    "difficulty": 1,
    "rating": 4.5,
    "orderCount": 120,
    "ingredients": ["ovos", "manteiga", "Sal a gosto"]
  },
  {
    "id": 2,
    "name": "Espaguete à Carbonara",
    "category": "Massa",
    "prepTime": 20,
    "cost": 18.00,
    "difficulty": 3,
    "rating": 4.8,
    "orderCount": 340,
    "ingredients": ["macarrão", "bacon", "gemas", "Queijo parmesão ralado", "Pimenta do reino"]
  },
  {
    "id": 3,
    "name": "Omelete Simples",
    "category": "Café da Manhã",
    "prepTime": 5,
    "cost": 3.00,
    "difficulty": 1,
    "rating": 4.2,
    "orderCount": 150,
    "ingredients": ["ovos", "sal", "pimenta do reino", "azeite"]
  },
  {
    "id": 4,
    "name": "Omelete com Queijo",
    "category": "Café da Manhã",
    "prepTime": 6,
    "cost": 4.50,
    "difficulty": 1,
    "rating": 4.6,
    "orderCount": 310,
    "ingredients": ["ovos", "queijo muçarela", "sal", "manteiga"]
  },
  {
    "id": 5,
    "name": "Omelete de Presunto e Queijo",
    "category": "Café da Manhã",
    "prepTime": 7,
    "cost": 5.50,
    "difficulty": 1,
    "rating": 4.7,
    "orderCount": 280,
    "ingredients": ["ovos", "presunto", "queijo muçarela", "manteiga"]
  },
  {
    "id": 6,
    "name": "Omelete de Espinafre e Cogumelos",
    "category": "Café da Manhã",
    "prepTime": 8,
    "cost": 6.00,
    "difficulty": 2,
    "rating": 4.8,
    "orderCount": 190,
    "ingredients": ["ovos", "cogumelos", "espinafre", "azeite"]
  },
  {
    "id": 7,
    "name": "Panqueca Clássica",
    "category": "Café da Manhã",
    "prepTime": 15,
    "cost": 4.00,
    "difficulty": 2,
    "rating": 4.5,
    "orderCount": 400,
    "ingredients": ["farinha de trigo", "leite", "ovos", "açúcar", "fermento", "mel"]
  },
  {
    "id": 8,
    "name": "Panqueca de Mirtilo",
    "category": "Café da Manhã",
    "prepTime": 18,
    "cost": 5.50,
    "difficulty": 2,
    "rating": 4.7,
    "orderCount": 350,
    "ingredients": ["farinha de trigo", "leite", "ovos", "mirtilos", "mel"]
  },
  {
    "id": 9,
    "name": "Panqueca com Gotas de Chocolate",
    "category": "Café da Manhã",
    "prepTime": 18,
    "cost": 5.00,
    "difficulty": 2,
    "rating": 4.8,
    "orderCount": 380,
    "ingredients": ["farinha de trigo", "leite", "ovos", "gotas de chocolate", "mel"]
  },
  {
    "id": 10,
    "name": "Espaguete à Bolonhesa",
    "category": "Massa",
    "prepTime": 40,
    "cost": 15.00,
    "difficulty": 2,
    "rating": 4.6,
    "orderCount": 420,
    "ingredients": ["macarrão", "carne moída", "molho de tomate", "cebola", "alho"]
  },
  {
    "id": 11,
    "name": "Espaguete Alho e Óleo",
    "category": "Massa",
    "prepTime": 15,
    "cost": 8.00,
    "difficulty": 1,
    "rating": 4.3,
    "orderCount": 250,
    "ingredients": ["macarrão", "alho", "azeite", "pimenta calabresa", "salsinha"]
  },
  {
    "id": 12,
    "name": "Fettuccine Alfredo",
    "category": "Massa",
    "prepTime": 20,
    "cost": 14.00,
    "difficulty": 2,
    "rating": 4.7,
    "orderCount": 390,
    "ingredients": ["fettuccine", "creme de leite fresco", "manteiga", "queijo parmesão", "alho"]
  },
  {
    "id": 13,
    "name": "Fettuccine Alfredo com Frango",
    "category": "Massa",
    "prepTime": 30,
    "cost": 19.00,
    "difficulty": 2,
    "rating": 4.9,
    "orderCount": 450,
    "ingredients": ["fettuccine", "peito de frango", "creme de leite fresco", "manteiga", "queijo parmesão"]
  },
  {
    "id": 14,
    "name": "Peito de Frango Grelhado",
    "category": "Prato Principal",
    "prepTime": 15,
    "cost": 10.00,
    "difficulty": 1,
    "rating": 4.4,
    "orderCount": 300,
    "ingredients": ["peito de frango", "azeite", "sal", "pimenta do reino", "suco de limão"]
  },
  {
    "id": 15,
    "name": "Frango ao Molho Barbecue",
    "category": "Prato Principal",
    "prepTime": 20,
    "cost": 12.00,
    "difficulty": 1,
    "rating": 4.6,
    "orderCount": 320,
    "ingredients": ["peito de frango", "molho barbecue", "azeite", "alho em pó"]
  },
  {
    "id": 16,
    "name": "Frango Lemon Pepper",
    "category": "Prato Principal",
    "prepTime": 18,
    "cost": 11.00,
    "difficulty": 1,
    "rating": 4.5,
    "orderCount": 280,
    "ingredients": ["peito de frango", "tempero lemon pepper", "manteiga", "azeite"]
  },
  {
    "id": 17,
    "name": "Frango ao Curry",
    "category": "Prato Principal",
    "prepTime": 35,
    "cost": 15.00,
    "difficulty": 3,
    "rating": 4.8,
    "orderCount": 220,
    "ingredients": ["frango", "curry em pó", "leite de coco", "cebola", "alho"]
  },
  {
    "id": 18,
    "name": "Hambúrguer Clássico",
    "category": "Fast Food",
    "prepTime": 15,
    "cost": 8.50,
    "difficulty": 1,
    "rating": 4.5,
    "orderCount": 500,
    "ingredients": ["carne de hambúrguer", "pão de hambúrguer", "alface", "tomate", "ketchup"]
  },
  {
    "id": 19,
    "name": "Cheeseburger",
    "category": "Fast Food",
    "prepTime": 16,
    "cost": 9.50,
    "difficulty": 1,
    "rating": 4.7,
    "orderCount": 650,
    "ingredients": ["carne de hambúrguer", "queijo cheddar", "pão de hambúrguer", "alface", "tomate"]
  },
  {
    "id": 20,
    "name": "Bacon Cheeseburger",
    "category": "Fast Food",
    "prepTime": 20,
    "cost": 12.00,
    "difficulty": 2,
    "rating": 4.9,
    "orderCount": 550,
    "ingredients": ["carne de hambúrguer", "bacon", "queijo cheddar", "pão de hambúrguer", "molho barbecue"]
  },
  {
    "id": 21,
    "name": "Double Cheeseburger",
    "category": "Fast Food",
    "prepTime": 20,
    "cost": 14.00,
    "difficulty": 2,
    "rating": 4.8,
    "orderCount": 480,
    "ingredients": ["2 carnes de hambúrguer", "2 fatias de queijo cheddar", "pão de hambúrguer", "picles"]
  },
  {
    "id": 22,
    "name": "Bife Grelhado",
    "category": "Prato Principal",
    "prepTime": 25,
    "cost": 25.00,
    "difficulty": 2,
    "rating": 4.9,
    "orderCount": 210,
    "ingredients": ["bife ancho", "sal grosso", "pimenta do reino", "manteiga", "alecrim"]
  },
  {
    "id": 23,
    "name": "Carne de Panela",
    "category": "Prato Principal",
    "prepTime": 120,
    "cost": 18.00,
    "difficulty": 3,
    "rating": 4.7,
    "orderCount": 160,
    "ingredients": ["carne bovina em cubos", "batatas", "cenouras", "caldo de carne", "cebolas"]
  },
  {
    "id": 24,
    "name": "Salada Verde",
    "category": "Salada",
    "prepTime": 10,
    "cost": 5.00,
    "difficulty": 1,
    "rating": 4.2,
    "orderCount": 180,
    "ingredients": ["alface", "tomates", "pepinos", "cebola roxa", "vinagrete"]
  },
  {
    "id": 25,
    "name": "Salada Caesar",
    "category": "Salada",
    "prepTime": 12,
    "cost": 7.00,
    "difficulty": 1,
    "rating": 4.6,
    "orderCount": 290,
    "ingredients": ["alface romana", "croutons", "queijo parmesão", "molho caesar"]
  },
  {
    "id": 26,
    "name": "Salada Caesar com Frango",
    "category": "Salada",
    "prepTime": 20,
    "cost": 11.00,
    "difficulty": 2,
    "rating": 4.8,
    "orderCount": 340,
    "ingredients": ["alface romana", "frango grelhado", "croutons", "queijo parmesão", "molho caesar"]
  },
  {
    "id": 27,
    "name": "Salada Grega",
    "category": "Salada",
    "prepTime": 15,
    "cost": 9.00,
    "difficulty": 1,
    "rating": 4.7,
    "orderCount": 210,
    "ingredients": ["pepinos", "tomates", "cebola roxa", "queijo feta", "azeitonas pretas", "azeite"]
  },
  {
    "id": 28,
    "name": "Misto Quente",
    "category": "Lanche",
    "prepTime": 10,
    "cost": 4.00,
    "difficulty": 1,
    "rating": 4.4,
    "orderCount": 420,
    "ingredients": ["pão de forma", "queijo prato", "presunto", "manteiga"]
  },
  {
    "id": 29,
    "name": "Sanduíche de Queijo Quente",
    "category": "Lanche",
    "prepTime": 5,
    "cost": 5.00,
    "difficulty": 1,
    "rating": 4.3,
    "orderCount": 380,
    "ingredients": ["pão de forma", "queijo muçarela", "manteiga"]
  },
  {
    "id": 30,
    "name": "Sanduíche BLT",
    "category": "Lanche",
    "prepTime": 12,
    "cost": 7.00,
    "difficulty": 1,
    "rating": 4.7,
    "orderCount": 310,
    "ingredients": ["pão de forma", "bacon", "alface", "tomate", "maionese"]
  },
  {
    "id": 31,
    "name": "Sanduíche de Peru",
    "category": "Lanche",
    "prepTime": 15,
    "cost": 9.50,
    "difficulty": 2,
    "rating": 4.8,
    "orderCount": 250,
    "ingredients": ["pão de forma", "peito de peru", "queijo branco", "alface", "tomate", "maionese"]
  },
  {
    "id": 32,
    "name": "Sanduíche de Atum",
    "category": "Lanche",
    "prepTime": 10,
    "cost": 6.50,
    "difficulty": 1,
    "rating": 4.5,
    "orderCount": 190,
    "ingredients": ["pão de forma", "atum em lata", "maionese", "cenoura ralada", "alface"]
  },
  {
    "id": 33,
    "name": "Arroz com Alho",
    "category": "Acompanhamento",
    "prepTime": 25,
    "cost": 4.00,
    "difficulty": 1,
    "rating": 4.4,
    "orderCount": 350,
    "ingredients": ["arroz branco", "água", "alho", "óleo", "sal"]
  },
  {
    "id": 34,
    "name": "Arroz Colorido",
    "category": "Acompanhamento",
    "prepTime": 20,
    "cost": 6.00,
    "difficulty": 2,
    "rating": 4.6,
    "orderCount": 280,
    "ingredients": ["arroz cozido", "cenoura", "ervilha", "milho", "ovos", "cebolinha"]
  },
  {
    "id": 35,
    "name": "Arroz Frito com Frango",
    "category": "Prato Principal",
    "prepTime": 25,
    "cost": 9.00,
    "difficulty": 2,
    "rating": 4.7,
    "orderCount": 320,
    "ingredients": ["arroz cozido", "peito de frango", "ervilha", "molho shoyu", "ovos", "óleo de gergelim"]
  },
  {
    "id": 36,
    "name": "Risoto de Cogumelos",
    "category": "Prato Principal",
    "prepTime": 40,
    "cost": 16.00,
    "difficulty": 3,
    "rating": 4.8,
    "orderCount": 150,
    "ingredients": ["arroz arbóreo", "cogumelos", "caldo de legumes", "queijo parmesão", "vinho branco"]
  },
  {
    "id": 37,
    "name": "Salmão Grelhado",
    "category": "Frutos do Mar",
    "prepTime": 20,
    "cost": 22.00,
    "difficulty": 2,
    "rating": 4.9,
    "orderCount": 200,
    "ingredients": ["filé de salmão", "azeite", "suco de limão", "sal", "pimenta do reino"]
  },
  {
    "id": 38,
    "name": "Camarão na Manteiga de Alho",
    "category": "Frutos do Mar",
    "prepTime": 15,
    "cost": 18.00,
    "difficulty": 2,
    "rating": 4.8,
    "orderCount": 240,
    "ingredients": ["camarão", "manteiga", "alho", "suco de limão", "salsinha"]
  },
  {
    "id": 39,
    "name": "Peixe Empanado com Fritas",
    "category": "Frutos do Mar",
    "prepTime": 35,
    "cost": 15.00,
    "difficulty": 3,
    "rating": 4.6,
    "orderCount": 310,
    "ingredients": ["filé de peixe branco", "farinha de trigo", "cerveja", "batatas", "molho tártaro", "óleo"]
  },
  {
    "id": 40,
    "name": "Macarrão com Frutos do Mar",
    "category": "Massa",
    "prepTime": 30,
    "cost": 24.00,
    "difficulty": 3,
    "rating": 4.7,
    "orderCount": 180,
    "ingredients": ["linguine", "camarão", "mariscos", "molho de tomate", "alho", "vinho branco"]
  },
  {
    "id": 41,
    "name": "Bolo de Chocolate Clássico",
    "category": "Sobremesa",
    "prepTime": 60,
    "cost": 12.00,
    "difficulty": 2,
    "rating": 4.9,
    "orderCount": 420,
    "ingredients": ["farinha de trigo", "açúcar", "cacau em pó", "ovos", "leite", "óleo"]
  },
  {
    "id": 42,
    "name": "Bolo de Baunilha",
    "category": "Sobremesa",
    "prepTime": 55,
    "cost": 10.00,
    "difficulty": 2,
    "rating": 4.5,
    "orderCount": 250,
    "ingredients": ["farinha de trigo", "açúcar", "manteiga", "ovos", "essência de baunilha"]
  },
  {
    "id": 43,
    "name": "Brownie de Chocolate",
    "category": "Sobremesa",
    "prepTime": 45,
    "cost": 8.00,
    "difficulty": 1,
    "rating": 4.8,
    "orderCount": 500,
    "ingredients": ["farinha de trigo", "açúcar", "cacau em pó", "manteiga", "ovos", "gotas de chocolate"]
  },
  {
    "id": 44,
    "name": "Cookies de Gotas de Chocolate",
    "category": "Sobremesa",
    "prepTime": 30,
    "cost": 6.00,
    "difficulty": 1,
    "rating": 4.7,
    "orderCount": 600,
    "ingredients": ["farinha de trigo", "açúcar mascavo", "manteiga", "ovos", "gotas de chocolate", "baunilha"]
  },
  {
    "id": 45,
    "name": "Torta de Maçã",
    "category": "Sobremesa",
    "prepTime": 90,
    "cost": 14.00,
    "difficulty": 3,
    "rating": 4.8,
    "orderCount": 210,
    "ingredients": ["massa de torta", "maçãs", "açúcar", "canela", "manteiga"]
  },
  {
    "id": 46,
    "name": "Bolo de Banana",
    "category": "Sobremesa",
    "prepTime": 60,
    "cost": 7.00,
    "difficulty": 1,
    "rating": 4.6,
    "orderCount": 340,
    "ingredients": ["bananas maduras", "farinha de trigo", "açúcar", "manteiga", "ovos", "bicarbonato de sódio"]
  },
  {
    "id": 47,
    "name": "Cheesecake de Morango",
    "category": "Sobremesa",
    "prepTime": 120,
    "cost": 20.00,
    "difficulty": 3,
    "rating": 4.9,
    "orderCount": 280,
    "ingredients": ["massa de biscoito", "cream cheese", "açúcar", "ovos", "morangos"]
  },
  {
    "id": 48,
    "name": "Sundae de Sorvete",
    "category": "Sobremesa",
    "prepTime": 5,
    "cost": 5.00,
    "difficulty": 1,
    "rating": 4.7,
    "orderCount": 390,
    "ingredients": ["sorvete de baunilha", "calda de chocolate", "chantilly", "cereja"]
  },
  {
    "id": 49,
    "name": "Salada de Frutas",
    "category": "Sobremesa",
    "prepTime": 15,
    "cost": 8.00,
    "difficulty": 1,
    "rating": 4.5,
    "orderCount": 230,
    "ingredients": ["maçãs", "bananas", "uvas", "morangos", "mel"]
  },
  {
    "id": 50,
    "name": "Tiramisu",
    "category": "Sobremesa",
    "prepTime": 40,
    "cost": 18.00,
    "difficulty": 3,
    "rating": 4.9,
    "orderCount": 170,
    "ingredients": ["biscoito champagne", "queijo mascarpone", "café", "cacau em pó", "açúcar", "ovos"]
  }
]